{"version": 0.6, "generator": "Overpass API 0.7.59.5 b201bb38", "osm3s": {"timestamp_osm_base": "2023-04-13T14:11:54Z", "copyright": "The data included in this document is from www.openstreetmap.org. The data is made available under ODbL."}, "elements": [{"type": "node", "id": 31606807, "lat": 43.3813541, "lon": -8.3968086, "tags": {"source": "PGS"}}, {"type": "node", "id": 31610575, "lat": 43.3866681, "lon": -8.399869, "tags": {"source": "PGS"}}, {"type": "node", "id": 31618230, "lat": 43.3787378, "lon": -8.4079882, "tags": {"source": "PGS"}}, {"type": "node", "id": 31618756, "lat": 43.3816306, "lon": -8.3965248, "tags": {"source": "PGS"}}, {"type": "node", "id": 31620591, "lat": 43.3872874, "lon": -8.399406, "tags": {"source": "PGS"}}, {"type": "node", "id": 31622371, "lat": 43.3775383, "lon": -8.4250628, "tags": {"source": "PGS"}}, {"type": "node", "id": 31626707, "lat": 43.3842508, "lon": -8.4062654, "tags": {"source": "PGS"}}, {"type": "node", "id": 31627679, "lat": 43.3819332, "lon": -8.3959551, "tags": {"source": "PGS"}}, {"type": "node", "id": 31635031, "lat": 43.3865238, "lon": -8.3958047, "tags": {"source": "PGS"}}, {"type": "node", "id": 472690415, "lat": 43.3692416, "lon": -8.407694}, {"type": "node", "id": 472690416, "lat": 43.3692222, "lon": -8.4075882}, {"type": "node", "id": 472690417, "lat": 43.3699283, "lon": -8.4059355}, {"type": "node", "id": 472690418, "lat": 43.3702126, "lon": -8.4055437}, {"type": "node", "id": 472690419, "lat": 43.370792, "lon": -8.4049417}, {"type": "node", "id": 472690420, "lat": 43.3713801, "lon": -8.4043857}, {"type": "node", "id": 472690421, "lat": 43.3723578, "lon": -8.4035841}, {"type": "node", "id": 472690423, "lat": 43.3731871, "lon": -8.4030278}, {"type": "node", "id": 472690424, "lat": 43.3736496, "lon": -8.4029231}, {"type": "node", "id": 472690425, "lat": 43.3741135, "lon": -8.4029692}, {"type": "node", "id": 472690426, "lat": 43.3743542, "lon": -8.4031312}, {"type": "node", "id": 472690429, "lat": 43.3752217, "lon": -8.4034683}, {"type": "node", "id": 472690430, "lat": 43.3754634, "lon": -8.4034376}, {"type": "node", "id": 472690431, "lat": 43.375666, "lon": -8.4035518}, {"type": "node", "id": 472690432, "lat": 43.3758196, "lon": -8.403838}, {"type": "node", "id": 472690434, "lat": 43.369642, "lon": -8.4148168}, {"type": "node", "id": 472690435, "lat": 43.3694729, "lon": -8.4147775}, {"type": "node", "id": 472690436, "lat": 43.3691284, "lon": -8.4143394}, {"type": "node", "id": 472690437, "lat": 43.3687049, "lon": -8.4135503}, {"type": "node", "id": 472690438, "lat": 43.3682996, "lon": -8.4126162}, {"type": "node", "id": 472690439, "lat": 43.3682078, "lon": -8.4119548}, {"type": "node", "id": 472690440, "lat": 43.3682316, "lon": -8.4113677}, {"type": "node", "id": 472690441, "lat": 43.3684801, "lon": -8.4100026}, {"type": "node", "id": 472690442, "lat": 43.3686752, "lon": -8.4090504}, {"type": "node", "id": 472690443, "lat": 43.3688929, "lon": -8.4083067}, {"type": "node", "id": 472690444, "lat": 43.3691955, "lon": -8.407941}, {"type": "node", "id": 480761387, "lat": 43.3738463, "lon": -8.4193828}, {"type": "node", "id": 480761388, "lat": 43.3739902, "lon": -8.4193994}, {"type": "node", "id": 480761428, "lat": 43.3771796, "lon": -8.4254449}, {"type": "node", "id": 480939708, "lat": 43.381566, "lon": -8.3975223}, {"type": "node", "id": 480939714, "lat": 43.3816908, "lon": -8.3974966}, {"type": "node", "id": 480939718, "lat": 43.3818592, "lon": -8.3973764}, {"type": "node", "id": 480939723, "lat": 43.3820214, "lon": -8.397179}, {"type": "node", "id": 480939734, "lat": 43.3820697, "lon": -8.3969809}, {"type": "node", "id": 480939740, "lat": 43.382177, "lon": -8.3968242}, {"type": "node", "id": 480939745, "lat": 43.3822019, "lon": -8.3966622}, {"type": "node", "id": 480939754, "lat": 43.382194, "lon": -8.3965048}, {"type": "node", "id": 843945206, "lat": 43.3842748, "lon": -8.3925498}, {"type": "node", "id": 843945209, "lat": 43.3844541, "lon": -8.3925069}, {"type": "node", "id": 843945224, "lat": 43.3837836, "lon": -8.3934939}, {"type": "node", "id": 843945226, "lat": 43.3838693, "lon": -8.3934296}, {"type": "node", "id": 843945427, "lat": 43.3864637, "lon": -8.395336}, {"type": "node", "id": 843945429, "lat": 43.3864739, "lon": -8.3955012}, {"type": "node", "id": 844086949, "lat": 43.3858966, "lon": -8.3953715}, {"type": "node", "id": 844086950, "lat": 43.3858838, "lon": -8.3955941}, {"type": "node", "id": 844086952, "lat": 43.3858897, "lon": -8.3959017}, {"type": "node", "id": 844086953, "lat": 43.385963, "lon": -8.3961298}, {"type": "node", "id": 844086954, "lat": 43.3861305, "lon": -8.3961869}, {"type": "node", "id": 844086958, "lat": 43.3838927, "lon": -8.3936978}, {"type": "node", "id": 844086959, "lat": 43.3840097, "lon": -8.393848}, {"type": "node", "id": 844086960, "lat": 43.3840409, "lon": -8.3939446}, {"type": "node", "id": 844086961, "lat": 43.3841344, "lon": -8.3940197}, {"type": "node", "id": 844086962, "lat": 43.3841734, "lon": -8.393966}, {"type": "node", "id": 844086963, "lat": 43.3841422, "lon": -8.3938373}, {"type": "node", "id": 844086964, "lat": 43.3840565, "lon": -8.39373}, {"type": "node", "id": 844086967, "lat": 43.3840097, "lon": -8.3935583}, {"type": "node", "id": 844086971, "lat": 43.3845633, "lon": -8.3925927}, {"type": "node", "id": 844086973, "lat": 43.3845867, "lon": -8.392818}, {"type": "node", "id": 844086975, "lat": 43.3845205, "lon": -8.3929595}, {"type": "node", "id": 844086976, "lat": 43.3843762, "lon": -8.3928717}, {"type": "node", "id": 844086978, "lat": 43.384306, "lon": -8.3927107}, {"type": "node", "id": 844086989, "lat": 43.3841377, "lon": -8.4060441}, {"type": "node", "id": 844086991, "lat": 43.3840026, "lon": -8.4059232}, {"type": "node", "id": 844086997, "lat": 43.3838934, "lon": -8.4055451}, {"type": "node", "id": 844086998, "lat": 43.3836337, "lon": -8.4055984}, {"type": "node", "id": 844087000, "lat": 43.3835808, "lon": -8.4057785}, {"type": "node", "id": 844087004, "lat": 43.3834405, "lon": -8.4059179}, {"type": "node", "id": 844087005, "lat": 43.3833233, "lon": -8.4063272}, {"type": "node", "id": 844087008, "lat": 43.3833647, "lon": -8.4064326}, {"type": "node", "id": 844087011, "lat": 43.3834717, "lon": -8.4065939}, {"type": "node", "id": 1695373521, "lat": 43.3699732, "lon": -8.4143648}, {"type": "node", "id": 1695373524, "lat": 43.371219, "lon": -8.4178574}, {"type": "node", "id": 1695373525, "lat": 43.3712388, "lon": -8.417923}, {"type": "node", "id": 1695373526, "lat": 43.3712658, "lon": -8.4177858}, {"type": "node", "id": 1695373528, "lat": 43.3713456, "lon": -8.4180086}, {"type": "node", "id": 1695373546, "lat": 43.3723351, "lon": -8.418555}, {"type": "node", "id": 1695373548, "lat": 43.3723865, "lon": -8.4186394}, {"type": "node", "id": 1695373549, "lat": 43.3723347, "lon": -8.418423}, {"type": "node", "id": 1695373550, "lat": 43.3724519, "lon": -8.4186828}, {"type": "node", "id": 1695373551, "lat": 43.3725265, "lon": -8.418708}, {"type": "node", "id": 1695373562, "lat": 43.3746434, "lon": -8.4038123}, {"type": "node", "id": 1695373571, "lat": 43.3750239, "lon": -8.4039984}, {"type": "node", "id": 1695373581, "lat": 43.3788513, "lon": -8.4080963}, {"type": "node", "id": 1695377134, "lat": 43.3868125, "lon": -8.3997563}, {"type": "node", "id": 1712869471, "lat": 43.3738132, "lon": -8.4197016}, {"type": "node", "id": 1712869477, "lat": 43.3741186, "lon": -8.4194054}, {"type": "node", "id": 1712869480, "lat": 43.3741698, "lon": -8.4194702}, {"type": "node", "id": 1712869483, "lat": 43.3741961, "lon": -8.4195886}, {"type": "node", "id": 1712869489, "lat": 43.3741323, "lon": -8.4197053}, {"type": "node", "id": 1870878266, "lat": 43.3835992, "lon": -8.4056701}, {"type": "node", "id": 1870878267, "lat": 43.3836075, "lon": -8.4057078}, {"type": "node", "id": 1870878271, "lat": 43.3839364, "lon": -8.4056176}, {"type": "node", "id": 1870878273, "lat": 43.3839686, "lon": -8.4057373}, {"type": "node", "id": 1870878274, "lat": 43.3839585, "lon": -8.4057643}, {"type": "node", "id": 1870878275, "lat": 43.3839585, "lon": -8.4057922}, {"type": "node", "id": 1870878278, "lat": 43.3840699, "lon": -8.4059824}, {"type": "node", "id": 1870878279, "lat": 43.3840985, "lon": -8.405989}, {"type": "node", "id": 1870878280, "lat": 43.3841211, "lon": -8.4060103}, {"type": "node", "id": 1870878281, "lat": 43.3841414, "lon": -8.4060931}, {"type": "node", "id": 1870878283, "lat": 43.3842314, "lon": -8.4061956}, {"type": "node", "id": 2144030343, "lat": 43.3714495, "lon": -8.41847}, {"type": "node", "id": 2144030349, "lat": 43.3712352, "lon": -8.4177356}, {"type": "node", "id": 2144030351, "lat": 43.3720584, "lon": -8.4189386}, {"type": "node", "id": 2144030355, "lat": 43.3710014, "lon": -8.4178453}, {"type": "node", "id": 2144030365, "lat": 43.3722686, "lon": -8.4185724}, {"type": "node", "id": 2144030372, "lat": 43.37219, "lon": -8.4187841}, {"type": "node", "id": 2144030381, "lat": 43.3725267, "lon": -8.4188482}, {"type": "node", "id": 2144030402, "lat": 43.3725429, "lon": -8.4190197}, {"type": "node", "id": 2144030421, "lat": 43.3711997, "lon": -8.4183474}, {"type": "node", "id": 2420101291, "lat": 43.3723198, "lon": -8.4190158}, {"type": "node", "id": 2420103239, "lat": 43.3714432, "lon": -8.4181265}, {"type": "node", "id": 2617061857, "lat": 43.386592, "lon": -8.3996485}, {"type": "node", "id": 2617061858, "lat": 43.3866036, "lon": -8.3995042}, {"type": "node", "id": 2617061859, "lat": 43.3866071, "lon": -8.3991605}, {"type": "node", "id": 2617061860, "lat": 43.3866089, "lon": -8.3996142}, {"type": "node", "id": 2617061861, "lat": 43.3866276, "lon": -8.3992669}, {"type": "node", "id": 2617061862, "lat": 43.3866354, "lon": -8.3991293}, {"type": "node", "id": 2617061864, "lat": 43.3866684, "lon": -8.3992291}, {"type": "node", "id": 3018266453, "lat": 43.3789925, "lon": -8.4087311}, {"type": "node", "id": 3018266454, "lat": 43.3791425, "lon": -8.4089472}, {"type": "node", "id": 3018266456, "lat": 43.3790523, "lon": -8.4081472}, {"type": "node", "id": 3306648907, "lat": 43.3757575, "lon": -8.4036971}, {"type": "node", "id": 3306648933, "lat": 43.3755156, "lon": -8.4034596}, {"type": "node", "id": 4582881691, "lat": 43.3869651, "lon": -8.3989782}, {"type": "node", "id": 4582881723, "lat": 43.3867993, "lon": -8.3994368}, {"type": "node", "id": 4582881736, "lat": 43.3869827, "lon": -8.399174}, {"type": "node", "id": 4582881750, "lat": 43.3870391, "lon": -8.399241}, {"type": "node", "id": 4582881799, "lat": 43.3869827, "lon": -8.3988172}, {"type": "node", "id": 4582881800, "lat": 43.3871424, "lon": -8.3989513}, {"type": "node", "id": 4582881807, "lat": 43.38685, "lon": -8.3995146}, {"type": "node", "id": 4582881818, "lat": 43.3867682, "lon": -8.3993429}, {"type": "node", "id": 4884182014, "lat": 43.3698348, "lon": -8.4061676}, {"type": "node", "id": 4884182015, "lat": 43.3699241, "lon": -8.4059947}, {"type": "node", "id": 4884196710, "lat": 43.3685947, "lon": -8.409515}, {"type": "node", "id": 4884196711, "lat": 43.3686804, "lon": -8.4091035}, {"type": "node", "id": 5036761344, "lat": 43.3758473, "lon": -8.4043547}, {"type": "node", "id": 5036761405, "lat": 43.3770328, "lon": -8.4247924}, {"type": "node", "id": 5036761555, "lat": 43.3770184, "lon": -8.4248322}, {"type": "node", "id": 5036761566, "lat": 43.3745223, "lon": -8.4034188}, {"type": "node", "id": 5036761585, "lat": 43.3773707, "lon": -8.4247484}, {"type": "node", "id": 5036761596, "lat": 43.3693636, "lon": -8.408006}, {"type": "node", "id": 5036761604, "lat": 43.3750612, "lon": -8.4039418}, {"type": "node", "id": 5036761610, "lat": 43.3836885, "lon": -8.4066166}, {"type": "node", "id": 5036761612, "lat": 43.3843182, "lon": -8.4065997}, {"type": "node", "id": 5406109821, "lat": 43.3695592, "lon": -8.4080783}, {"type": "node", "id": 5406109822, "lat": 43.3697439, "lon": -8.4080496}, {"type": "node", "id": 5406109823, "lat": 43.3696485, "lon": -8.4080476}, {"type": "node", "id": 5406109826, "lat": 43.369381, "lon": -8.4078064}, {"type": "node", "id": 5406109828, "lat": 43.3692407, "lon": -8.4077469}, {"type": "node", "id": 5406109831, "lat": 43.3692358, "lon": -8.4076352}, {"type": "node", "id": 5406109833, "lat": 43.3710002, "lon": -8.4048089}, {"type": "node", "id": 5406109834, "lat": 43.3708437, "lon": -8.4049279}, {"type": "node", "id": 5406109835, "lat": 43.3709902, "lon": -8.4047885}, {"type": "node", "id": 5406109838, "lat": 43.3728674, "lon": -8.4032743}, {"type": "node", "id": 5406111541, "lat": 43.3742774, "lon": -8.4030684}, {"type": "node", "id": 5406111548, "lat": 43.3752036, "lon": -8.4035453}, {"type": "node", "id": 5406117848, "lat": 43.3746919, "lon": -8.4035037}, {"type": "node", "id": 5406117849, "lat": 43.3746952, "lon": -8.4036454}, {"type": "node", "id": 5499790213, "lat": 43.3871983, "lon": -8.3994581}, {"type": "node", "id": 5499790214, "lat": 43.3872346, "lon": -8.3990888}, {"type": "node", "id": 5499790390, "lat": 43.3818368, "lon": -8.3958867, "tags": {"source": "PGS"}}, {"type": "node", "id": 5499790391, "lat": 43.3814475, "lon": -8.3967551}, {"type": "node", "id": 5667204476, "lat": 43.3696463, "lon": -8.4147766}, {"type": "node", "id": 5667204482, "lat": 43.3698757, "lon": -8.4146838}, {"type": "node", "id": 5667204497, "lat": 43.369571, "lon": -8.4148117}, {"type": "node", "id": 5667204500, "lat": 43.3696496, "lon": -8.4147936}, {"type": "node", "id": 5667219025, "lat": 43.3695258, "lon": -8.4148032}, {"type": "node", "id": 5667219027, "lat": 43.3696073, "lon": -8.4148169}, {"type": "node", "id": 5667219028, "lat": 43.3693012, "lon": -8.4145881}, {"type": "node", "id": 5667248841, "lat": 43.3689046, "lon": -8.4139081}, {"type": "node", "id": 5667248867, "lat": 43.3690223, "lon": -8.4141697}, {"type": "node", "id": 5667248869, "lat": 43.3683438, "lon": -8.4127243}, {"type": "node", "id": 5667248880, "lat": 43.3688097, "lon": -8.4137814}, {"type": "node", "id": 5667248887, "lat": 43.3683806, "lon": -8.4128067}, {"type": "node", "id": 5667267311, "lat": 43.3682559, "lon": -8.4124575}, {"type": "node", "id": 5667267313, "lat": 43.3682509, "lon": -8.4123537}, {"type": "node", "id": 5667267314, "lat": 43.3682231, "lon": -8.4119541}, {"type": "node", "id": 5667267319, "lat": 43.3686578, "lon": -8.4134462}, {"type": "node", "id": 5667267629, "lat": 43.3685417, "lon": -8.4131401}, {"type": "node", "id": 5667267633, "lat": 43.3686002, "lon": -8.4132736}, {"type": "node", "id": 5667274023, "lat": 43.3689596, "lon": -8.414038}, {"type": "node", "id": 5667274026, "lat": 43.3688931, "lon": -8.4139199}, {"type": "node", "id": 5667281034, "lat": 43.3682008, "lon": -8.4117779}, {"type": "node", "id": 5667281036, "lat": 43.3682125, "lon": -8.4114886}, {"type": "node", "id": 5667281044, "lat": 43.3682029, "lon": -8.4116114}, {"type": "node", "id": 5667285722, "lat": 43.3683544, "lon": -8.4107631}, {"type": "node", "id": 5667285724, "lat": 43.3684023, "lon": -8.4104271}, {"type": "node", "id": 5667285726, "lat": 43.3683434, "lon": -8.4108236}, {"type": "node", "id": 5667285730, "lat": 43.3683278, "lon": -8.4108183}, {"type": "node", "id": 5667313602, "lat": 43.368576, "lon": -8.4095081}, {"type": "node", "id": 5667438975, "lat": 43.3687769, "lon": -8.4086764}, {"type": "node", "id": 5667468551, "lat": 43.3691847, "lon": -8.4075164}, {"type": "node", "id": 5667468555, "lat": 43.3694113, "lon": -8.4070051}, {"type": "node", "id": 5667468556, "lat": 43.3696308, "lon": -8.40807}, {"type": "node", "id": 5667468560, "lat": 43.3696039, "lon": -8.4080816}, {"type": "node", "id": 5667468561, "lat": 43.3687796, "lon": -8.4086678}, {"type": "node", "id": 5667492621, "lat": 43.3696028, "lon": -8.4065987}, {"type": "node", "id": 5667492628, "lat": 43.370014, "lon": -8.4057981}, {"type": "node", "id": 5667492630, "lat": 43.3697549, "lon": -8.4062777}, {"type": "node", "id": 5667492631, "lat": 43.3694132, "lon": -8.407001}, {"type": "node", "id": 5667501620, "lat": 43.3728939, "lon": -8.4032146}, {"type": "node", "id": 5667503722, "lat": 43.3733222, "lon": -8.4029825}, {"type": "node", "id": 5667503724, "lat": 43.3730486, "lon": -8.403095}, {"type": "node", "id": 5667503725, "lat": 43.3734701, "lon": -8.4029456}, {"type": "node", "id": 5667503727, "lat": 43.3718089, "lon": -8.4040136}, {"type": "node", "id": 5667503730, "lat": 43.3728846, "lon": -8.4031839}, {"type": "node", "id": 5667503737, "lat": 43.372553, "lon": -8.4034837}, {"type": "node", "id": 5667523640, "lat": 43.3739934, "lon": -8.4029477}, {"type": "node", "id": 5667523644, "lat": 43.3738192, "lon": -8.4029235}, {"type": "node", "id": 5667523645, "lat": 43.3742867, "lon": -8.4030254}, {"type": "node", "id": 5667523647, "lat": 43.374378, "lon": -8.4034357}, {"type": "node", "id": 5667523649, "lat": 43.3742394, "lon": -8.403006}, {"type": "node", "id": 5667523650, "lat": 43.3743584, "lon": -8.4033088}, {"type": "node", "id": 5667523651, "lat": 43.37427, "lon": -8.403103}, {"type": "node", "id": 5670442788, "lat": 43.3694123, "lon": -8.4147231}, {"type": "node", "id": 5670442789, "lat": 43.369358, "lon": -8.4146614}, {"type": "node", "id": 5670442790, "lat": 43.3692356, "lon": -8.4144976}, {"type": "node", "id": 5670442791, "lat": 43.3696537, "lon": -8.4148135}, {"type": "node", "id": 5670446528, "lat": 43.3688836, "lon": -8.4139297}, {"type": "node", "id": 5670446529, "lat": 43.3689701, "lon": -8.4140254}, {"type": "node", "id": 5670446530, "lat": 43.3689502, "lon": -8.4140494}, {"type": "node", "id": 5670446535, "lat": 43.3685545, "lon": -8.4131304}, {"type": "node", "id": 5670446536, "lat": 43.3685298, "lon": -8.4131492}, {"type": "node", "id": 5670446537, "lat": 43.3686111, "lon": -8.4132638}, {"type": "node", "id": 5670446538, "lat": 43.3685869, "lon": -8.4132858}, {"type": "node", "id": 5670446539, "lat": 43.3688474, "lon": -8.4138603}, {"type": "node", "id": 5670446540, "lat": 43.3687571, "lon": -8.4136669}, {"type": "node", "id": 5670446544, "lat": 43.3682739, "lon": -8.4125307}, {"type": "node", "id": 5670446545, "lat": 43.3682351, "lon": -8.4123586}, {"type": "node", "id": 5670446548, "lat": 43.3682657, "lon": -8.4123491}, {"type": "node", "id": 5670446549, "lat": 43.3682404, "lon": -8.4119532}, {"type": "node", "id": 5670446550, "lat": 43.3682562, "lon": -8.4122706}, {"type": "node", "id": 5670446551, "lat": 43.3682498, "lon": -8.4121743}, {"type": "node", "id": 5670446552, "lat": 43.3682451, "lon": -8.4120647}, {"type": "node", "id": 5670446555, "lat": 43.3683679, "lon": -8.4107679}, {"type": "node", "id": 5670446556, "lat": 43.3683387, "lon": -8.4107576}, {"type": "node", "id": 5670446557, "lat": 43.3683571, "lon": -8.4108283}, {"type": "node", "id": 5670446558, "lat": 43.3686945, "lon": -8.4091095}, {"type": "node", "id": 5670446559, "lat": 43.3686651, "lon": -8.409097}, {"type": "node", "id": 5670446560, "lat": 43.3686149, "lon": -8.4095224}, {"type": "node", "id": 5670446564, "lat": 43.3699407, "lon": -8.4060106}, {"type": "node", "id": 5670446565, "lat": 43.3699054, "lon": -8.4059756}, {"type": "node", "id": 5670446566, "lat": 43.3698513, "lon": -8.4061827}, {"type": "node", "id": 5670446567, "lat": 43.3698169, "lon": -8.4061507}, {"type": "node", "id": 5670446571, "lat": 43.3709785, "lon": -8.4047663}, {"type": "node", "id": 5670446572, "lat": 43.3708552, "lon": -8.4049495}, {"type": "node", "id": 5670446573, "lat": 43.3708308, "lon": -8.4049038}, {"type": "node", "id": 5670446576, "lat": 43.372878, "lon": -8.4033116}, {"type": "node", "id": 5670446577, "lat": 43.3728566, "lon": -8.4032365}, {"type": "node", "id": 5670446579, "lat": 43.3725639, "lon": -8.4035088}, {"type": "node", "id": 5670446580, "lat": 43.3726878, "lon": -8.4034131}, {"type": "node", "id": 5670446581, "lat": 43.3725415, "lon": -8.403456}, {"type": "node", "id": 5670446584, "lat": 43.3727783, "lon": -8.403356}, {"type": "node", "id": 5673396209, "lat": 43.3709949, "lon": -8.4179475}, {"type": "node", "id": 5673396210, "lat": 43.3710332, "lon": -8.4179157}, {"type": "node", "id": 5673396211, "lat": 43.3710125, "lon": -8.4179329}, {"type": "node", "id": 5673396213, "lat": 43.3712469, "lon": -8.4184191}, {"type": "node", "id": 5673396214, "lat": 43.3713702, "lon": -8.4185638}, {"type": "node", "id": 5673396215, "lat": 43.3714378, "lon": -8.4186249}, {"type": "node", "id": 5673397025, "lat": 43.3721242, "lon": -8.4188257}, {"type": "node", "id": 5673397034, "lat": 43.3720554, "lon": -8.4189711}, {"type": "node", "id": 5673397035, "lat": 43.3721617, "lon": -8.4189996}, {"type": "node", "id": 5673397053, "lat": 43.3720568, "lon": -8.4189559}, {"type": "node", "id": 5866419367, "lat": 43.3750419, "lon": -8.4038038}, {"type": "node", "id": 5866419368, "lat": 43.3751115, "lon": -8.4038902}, {"type": "node", "id": 5866419369, "lat": 43.3751025, "lon": -8.4039241}, {"type": "node", "id": 5866420693, "lat": 43.3758719, "lon": -8.4040061}, {"type": "node", "id": 5866420694, "lat": 43.3759244, "lon": -8.4042043}, {"type": "node", "id": 5866420696, "lat": 43.375954, "lon": -8.4043167}, {"type": "node", "id": 5866420851, "lat": 43.3757015, "lon": -8.4036081}, {"type": "node", "id": 5866440956, "lat": 43.3752111, "lon": -8.4035197}, {"type": "node", "id": 5866440960, "lat": 43.3751908, "lon": -8.4035904}, {"type": "node", "id": 5869331542, "lat": 43.3788769, "lon": -8.4082448}, {"type": "node", "id": 5869331543, "lat": 43.3789169, "lon": -8.4085616}, {"type": "node", "id": 5871750361, "lat": 43.3791501, "lon": -8.4084444}, {"type": "node", "id": 5871750383, "lat": 43.3788787, "lon": -8.4080003}, {"type": "node", "id": 5871750384, "lat": 43.3789513, "lon": -8.4080287}, {"type": "node", "id": 5871751285, "lat": 43.3791553, "lon": -8.4084187}, {"type": "node", "id": 5871751286, "lat": 43.3791272, "lon": -8.4085573}, {"type": "node", "id": 5871751287, "lat": 43.3792085, "lon": -8.4085978}, {"type": "node", "id": 5871751288, "lat": 43.3792498, "lon": -8.4087028}, {"type": "node", "id": 5871751289, "lat": 43.3792817, "lon": -8.4087218}, {"type": "node", "id": 5871751290, "lat": 43.3790608, "lon": -8.4088802}, {"type": "node", "id": 5871751291, "lat": 43.3792048, "lon": -8.4090119}, {"type": "node", "id": 5871751292, "lat": 43.3792692, "lon": -8.4090696}, {"type": "node", "id": 5871751293, "lat": 43.3793087, "lon": -8.4090395}, {"type": "node", "id": 5871751294, "lat": 43.3793612, "lon": -8.4089835}, {"type": "node", "id": 5871751295, "lat": 43.3793274, "lon": -8.4088199}, {"type": "node", "id": 5871751296, "lat": 43.3794219, "lon": -8.4090248}, {"type": "node", "id": 5872134802, "lat": 43.383355, "lon": -8.40609}, {"type": "node", "id": 5872149709, "lat": 43.3839022, "lon": -8.4064079}, {"type": "node", "id": 5872150594, "lat": 43.3836063, "lon": -8.4065654}, {"type": "node", "id": 5884526789, "lat": 43.3697951, "lon": -8.4142139}, {"type": "node", "id": 5884526823, "lat": 43.3700708, "lon": -8.4145902}, {"type": "node", "id": 5884526824, "lat": 43.3700655, "lon": -8.4145717}, {"type": "node", "id": 5884526825, "lat": 43.3700641, "lon": -8.414557}, {"type": "node", "id": 5884526826, "lat": 43.3700711, "lon": -8.4145385}, {"type": "node", "id": 5884526827, "lat": 43.3700765, "lon": -8.4145283}, {"type": "node", "id": 5884526828, "lat": 43.3700726, "lon": -8.4145195}, {"type": "node", "id": 5884526829, "lat": 43.3700641, "lon": -8.4145117}, {"type": "node", "id": 5884526830, "lat": 43.3700676, "lon": -8.4144961}, {"type": "node", "id": 5884526831, "lat": 43.3700733, "lon": -8.4144747}, {"type": "node", "id": 5884526832, "lat": 43.3700899, "lon": -8.4144342}, {"type": "node", "id": 5884526833, "lat": 43.3700913, "lon": -8.4144186}, {"type": "node", "id": 5884526834, "lat": 43.370085, "lon": -8.4144137}, {"type": "node", "id": 5884526835, "lat": 43.3700747, "lon": -8.4144201}, {"type": "node", "id": 5884526836, "lat": 43.3700616, "lon": -8.4144386}, {"type": "node", "id": 5884526837, "lat": 43.3700343, "lon": -8.4144781}, {"type": "node", "id": 5884526838, "lat": 43.3700194, "lon": -8.4144995}, {"type": "node", "id": 5884526839, "lat": 43.3700074, "lon": -8.4145024}, {"type": "node", "id": 5884526840, "lat": 43.3699967, "lon": -8.4144995}, {"type": "node", "id": 5884526841, "lat": 43.3699872, "lon": -8.4145102}, {"type": "node", "id": 5884526842, "lat": 43.3699943, "lon": -8.4145185}, {"type": "node", "id": 5884526843, "lat": 43.3700021, "lon": -8.4145244}, {"type": "node", "id": 5884526844, "lat": 43.3700003, "lon": -8.4145371}, {"type": "node", "id": 5884526845, "lat": 43.3699879, "lon": -8.4145507}, {"type": "node", "id": 5884526846, "lat": 43.3699804, "lon": -8.4145614}, {"type": "node", "id": 5884526847, "lat": 43.3699744, "lon": -8.4145741}, {"type": "node", "id": 5884526848, "lat": 43.369973, "lon": -8.4146024}, {"type": "node", "id": 5884526849, "lat": 43.3699645, "lon": -8.414618}, {"type": "node", "id": 5884526850, "lat": 43.3699404, "lon": -8.4146165}, {"type": "node", "id": 5884526851, "lat": 43.3699085, "lon": -8.4146063}, {"type": "node", "id": 5884526852, "lat": 43.3699032, "lon": -8.4145899}, {"type": "node", "id": 5884526853, "lat": 43.3698947, "lon": -8.4145824}, {"type": "node", "id": 5884526854, "lat": 43.3698929, "lon": -8.4145687}, {"type": "node", "id": 5884526855, "lat": 43.3698974, "lon": -8.4145185}, {"type": "node", "id": 5884526856, "lat": 43.3699023, "lon": -8.4145078}, {"type": "node", "id": 5884526857, "lat": 43.36992, "lon": -8.4145034}, {"type": "node", "id": 5884526858, "lat": 43.3699268, "lon": -8.4144939}, {"type": "node", "id": 5884526859, "lat": 43.3699307, "lon": -8.4144795}, {"type": "node", "id": 5884526860, "lat": 43.36993, "lon": -8.4144647}, {"type": "node", "id": 5884526861, "lat": 43.36994, "lon": -8.4144586}, {"type": "node", "id": 5884526862, "lat": 43.3698965, "lon": -8.414541}, {"type": "node", "id": 5884526864, "lat": 43.3698818, "lon": -8.4147042}, {"type": "node", "id": 5884526867, "lat": 43.3699078, "lon": -8.4145037}, {"type": "node", "id": 5884526868, "lat": 43.3699498, "lon": -8.4144596}, {"type": "node", "id": 5884526869, "lat": 43.3699571, "lon": -8.4144571}, {"type": "node", "id": 5884526870, "lat": 43.3699698, "lon": -8.4144639}, {"type": "node", "id": 5884526871, "lat": 43.3699804, "lon": -8.4144708}, {"type": "node", "id": 5884526872, "lat": 43.3699897, "lon": -8.4144591}, {"type": "node", "id": 5884526873, "lat": 43.3699907, "lon": -8.4144069}, {"type": "node", "id": 5884526874, "lat": 43.36999, "lon": -8.4143835}, {"type": "node", "id": 5884526875, "lat": 43.3699493, "lon": -8.414345}, {"type": "node", "id": 5884526876, "lat": 43.3699245, "lon": -8.4143187}, {"type": "node", "id": 5884526877, "lat": 43.3699167, "lon": -8.4142663}, {"type": "node", "id": 5884546681, "lat": 43.372239, "lon": -8.4190075}, {"type": "node", "id": 5884547309, "lat": 43.372372, "lon": -8.4190167}, {"type": "node", "id": 5884547357, "lat": 43.3725753, "lon": -8.4190192}, {"type": "node", "id": 5884547358, "lat": 43.3725743, "lon": -8.4189712}, {"type": "node", "id": 5884547359, "lat": 43.3725764, "lon": -8.4189512}, {"type": "node", "id": 5884547360, "lat": 43.3725642, "lon": -8.4189371}, {"type": "node", "id": 5884547361, "lat": 43.3725497, "lon": -8.4189203}, {"type": "node", "id": 5884547362, "lat": 43.3725383, "lon": -8.4188796}, {"type": "node", "id": 5884547363, "lat": 43.3725284, "lon": -8.4188272}, {"type": "node", "id": 5884547364, "lat": 43.3725348, "lon": -8.4188091}, {"type": "node", "id": 5884547365, "lat": 43.3725327, "lon": -8.4187831}, {"type": "node", "id": 5884547366, "lat": 43.3725242, "lon": -8.4187582}, {"type": "node", "id": 5884547367, "lat": 43.3725151, "lon": -8.4187433}, {"type": "node", "id": 5884547368, "lat": 43.3725233, "lon": -8.4187214}, {"type": "node", "id": 5884547373, "lat": 43.372499, "lon": -8.4186963}, {"type": "node", "id": 5884547374, "lat": 43.3724175, "lon": -8.4186641}, {"type": "node", "id": 5884547375, "lat": 43.3723571, "lon": -8.4185986}, {"type": "node", "id": 5884547376, "lat": 43.3723259, "lon": -8.418525}, {"type": "node", "id": 5884547377, "lat": 43.3723218, "lon": -8.4184938}, {"type": "node", "id": 5884547378, "lat": 43.3723252, "lon": -8.4184611}, {"type": "node", "id": 5884547379, "lat": 43.372197, "lon": -8.4187584}, {"type": "node", "id": 5884547380, "lat": 43.372192, "lon": -8.4187185}, {"type": "node", "id": 5884547381, "lat": 43.3721998, "lon": -8.4186946}, {"type": "node", "id": 5884547382, "lat": 43.37222, "lon": -8.4186678}, {"type": "node", "id": 5884547383, "lat": 43.3722207, "lon": -8.4186415}, {"type": "node", "id": 5884547384, "lat": 43.372242, "lon": -8.41862}, {"type": "node", "id": 5884547385, "lat": 43.3722427, "lon": -8.4185747}, {"type": "node", "id": 5884547386, "lat": 43.3722487, "lon": -8.4185615}, {"type": "node", "id": 5884547387, "lat": 43.3722703, "lon": -8.4185508}, {"type": "node", "id": 5884547388, "lat": 43.3722675, "lon": -8.4184948}, {"type": "node", "id": 5884547389, "lat": 43.3722852, "lon": -8.4184889}, {"type": "node", "id": 5884547390, "lat": 43.3723128, "lon": -8.4184879}, {"type": "node", "id": 5884547391, "lat": 43.3723142, "lon": -8.4184772}, {"type": "node", "id": 5884547392, "lat": 43.3723181, "lon": -8.4184397}, {"type": "node", "id": 5884547510, "lat": 43.37142, "lon": -8.4180736}, {"type": "node", "id": 5884547511, "lat": 43.371387, "lon": -8.4180381}, {"type": "node", "id": 5884547512, "lat": 43.3713041, "lon": -8.4179815}, {"type": "node", "id": 5884547513, "lat": 43.3712652, "lon": -8.4179455}, {"type": "node", "id": 5884547514, "lat": 43.3712194, "lon": -8.4178918}, {"type": "node", "id": 5884547515, "lat": 43.3712361, "lon": -8.4178348}, {"type": "node", "id": 5884547516, "lat": 43.3712499, "lon": -8.4178143}, {"type": "node", "id": 5884547517, "lat": 43.371268, "lon": -8.4177617}, {"type": "node", "id": 5884547518, "lat": 43.3712797, "lon": -8.4177417}, {"type": "node", "id": 5884547519, "lat": 43.3710763, "lon": -8.4177734}, {"type": "node", "id": 5884547520, "lat": 43.3711387, "lon": -8.4177383}, {"type": "node", "id": 5884547521, "lat": 43.371189, "lon": -8.4177266}, {"type": "node", "id": 5884547522, "lat": 43.3714582, "lon": -8.4182978}, {"type": "node", "id": 5884563396, "lat": 43.3714528, "lon": -8.4184039}, {"type": "node", "id": 5884563413, "lat": 43.374018, "lon": -8.4194262}, {"type": "node", "id": 5884563414, "lat": 43.3740301, "lon": -8.4194286}, {"type": "node", "id": 5884563415, "lat": 43.3740442, "lon": -8.4194125}, {"type": "node", "id": 5884563416, "lat": 43.3740573, "lon": -8.4194111}, {"type": "node", "id": 5884563417, "lat": 43.3740694, "lon": -8.4194286}, {"type": "node", "id": 5884563418, "lat": 43.3740836, "lon": -8.4194286}, {"type": "node", "id": 5884563419, "lat": 43.3740956, "lon": -8.4194159}, {"type": "node", "id": 5884563420, "lat": 43.3741846, "lon": -8.4195397}, {"type": "node", "id": 5884563421, "lat": 43.3741734, "lon": -8.4195575}, {"type": "node", "id": 5884563423, "lat": 43.3741774, "lon": -8.4196726}, {"type": "node", "id": 5884563424, "lat": 43.3740829, "lon": -8.4197352}, {"type": "node", "id": 5884563425, "lat": 43.3740294, "lon": -8.4197776}, {"type": "node", "id": 5884563427, "lat": 43.3739664, "lon": -8.4197551}, {"type": "node", "id": 5884563428, "lat": 43.3739255, "lon": -8.4197498}, {"type": "node", "id": 5884563429, "lat": 43.3738572, "lon": -8.419742}, {"type": "node", "id": 5884563430, "lat": 43.3738384, "lon": -8.4197342}, {"type": "node", "id": 5884578511, "lat": 43.37395, "lon": -8.4194159}, {"type": "node", "id": 5884578512, "lat": 43.3738894, "lon": -8.4194081}, {"type": "node", "id": 5884578513, "lat": 43.3738225, "lon": -8.4196665}, {"type": "node", "id": 5884578514, "lat": 43.373831, "lon": -8.4195865}, {"type": "node", "id": 5884578515, "lat": 43.3738345, "lon": -8.4195271}, {"type": "node", "id": 5884578516, "lat": 43.3738271, "lon": -8.4194832}, {"type": "node", "id": 5884578517, "lat": 43.3738345, "lon": -8.4194242}, {"type": "node", "id": 5884578601, "lat": 43.37399, "lon": -8.4198442}, {"type": "node", "id": 5884578602, "lat": 43.3739837, "lon": -8.4198098}, {"type": "node", "id": 5884996913, "lat": 43.3739498, "lon": -8.4197474}, {"type": "node", "id": 5884998005, "lat": 43.3740015, "lon": -8.4198447}, {"type": "node", "id": 5885001881, "lat": 43.3738688, "lon": -8.4197433}, {"type": "node", "id": 5885137897, "lat": 43.3771505, "lon": -8.4253698}, {"type": "node", "id": 5885137898, "lat": 43.3771162, "lon": -8.4252998}, {"type": "node", "id": 5885137899, "lat": 43.3771137, "lon": -8.4252222}, {"type": "node", "id": 5885137900, "lat": 43.3770855, "lon": -8.425094}, {"type": "node", "id": 5885137901, "lat": 43.3770694, "lon": -8.4250268}, {"type": "node", "id": 5885137902, "lat": 43.3770517, "lon": -8.4249478}, {"type": "node", "id": 5885137903, "lat": 43.3770195, "lon": -8.4248902}, {"type": "node", "id": 5885137904, "lat": 43.377087, "lon": -8.4251349}, {"type": "node", "id": 5885137905, "lat": 43.377494, "lon": -8.4250676}, {"type": "node", "id": 5885137906, "lat": 43.3771857, "lon": -8.4253774}, {"type": "node", "id": 5885137907, "lat": 43.3772094, "lon": -8.4253102}, {"type": "node", "id": 5885137908, "lat": 43.3772386, "lon": -8.4252631}, {"type": "node", "id": 5885137909, "lat": 43.3772829, "lon": -8.4252014}, {"type": "node", "id": 5885137910, "lat": 43.3773333, "lon": -8.4251446}, {"type": "node", "id": 5885137911, "lat": 43.3773912, "lon": -8.4251058}, {"type": "node", "id": 5885137912, "lat": 43.3774477, "lon": -8.4250829}, {"type": "node", "id": 5885139212, "lat": 43.3774114, "lon": -8.4248133}, {"type": "node", "id": 5885139213, "lat": 43.3773242, "lon": -8.4247094}, {"type": "node", "id": 5885139214, "lat": 43.3772769, "lon": -8.4246823}, {"type": "node", "id": 5885139215, "lat": 43.3772311, "lon": -8.4246865}, {"type": "node", "id": 5885139216, "lat": 43.3771963, "lon": -8.4246976}, {"type": "node", "id": 5885139217, "lat": 43.3771641, "lon": -8.4247302}, {"type": "node", "id": 5885139218, "lat": 43.3771202, "lon": -8.4247773}, {"type": "node", "id": 5885139219, "lat": 43.3770724, "lon": -8.4247988}, {"type": "node", "id": 5885266205, "lat": 43.36987, "lon": -8.4146648}, {"type": "node", "id": 6096930442, "lat": 43.375213, "lon": -8.4035106}, {"type": "node", "id": 6314600545, "lat": 43.3692414, "lon": -8.4077062}, {"type": "node", "id": 6314600547, "lat": 43.3692073, "lon": -8.4075597}, {"type": "node", "id": 6399259994, "lat": 43.3700743, "lon": -8.4146111}, {"type": "node", "id": 6399259995, "lat": 43.3699922, "lon": -8.4146479}, {"type": "node", "id": 6486398130, "lat": 43.382131, "lon": -8.3968801}, {"type": "node", "id": 6486398131, "lat": 43.3821455, "lon": -8.396897}, {"type": "node", "id": 6486398136, "lat": 43.3820286, "lon": -8.3961089}, {"type": "node", "id": 6486398137, "lat": 43.3821212, "lon": -8.3970425}, {"type": "node", "id": 6486398139, "lat": 43.3822014, "lon": -8.3967435}, {"type": "node", "id": 6486398143, "lat": 43.3821652, "lon": -8.3963501}, {"type": "node", "id": 6486398146, "lat": 43.382122, "lon": -8.3962508}, {"type": "node", "id": 6772395983, "lat": 43.3751464, "lon": -8.4037462}, {"type": "node", "id": 6772415741, "lat": 43.3818318, "lon": -8.396034}, {"type": "node", "id": 6772415742, "lat": 43.3817534, "lon": -8.3962836}, {"type": "node", "id": 6772415743, "lat": 43.3813275, "lon": -8.3969284}, {"type": "node", "id": 6772415744, "lat": 43.3812926, "lon": -8.3968679}, {"type": "node", "id": 6772415753, "lat": 43.3835687, "lon": -8.4065435}, {"type": "node", "id": 6772415754, "lat": 43.3835409, "lon": -8.406544}, {"type": "node", "id": 6772415755, "lat": 43.383513, "lon": -8.4065813}, {"type": "node", "id": 6772415756, "lat": 43.3834924, "lon": -8.4065999}, {"type": "node", "id": 6772428685, "lat": 43.3746544, "lon": -8.4034409}, {"type": "node", "id": 6773051669, "lat": 43.3696603, "lon": -8.408013}, {"type": "node", "id": 6773051672, "lat": 43.3696592, "lon": -8.4079804}, {"type": "node", "id": 6773051673, "lat": 43.3696477, "lon": -8.4079529}, {"type": "node", "id": 6773051675, "lat": 43.3696255, "lon": -8.4079236}, {"type": "node", "id": 6773051677, "lat": 43.369598, "lon": -8.4079012}, {"type": "node", "id": 6773275378, "lat": 43.3837496, "lon": -8.4065014}, {"type": "node", "id": 6773275379, "lat": 43.3838259, "lon": -8.4064301}, {"type": "node", "id": 6773275380, "lat": 43.3839862, "lon": -8.4063848}, {"type": "node", "id": 6773275381, "lat": 43.3840748, "lon": -8.4063937}, {"type": "node", "id": 6773275382, "lat": 43.3841941, "lon": -8.4064667, "tags": {"source": "PGS"}}, {"type": "node", "id": 6775537447, "lat": 43.3757118, "lon": -8.4042242}, {"type": "node", "id": 6775537449, "lat": 43.3755556, "lon": -8.4041501}, {"type": "node", "id": 6775537450, "lat": 43.3753772, "lon": -8.4040724}, {"type": "node", "id": 6775537451, "lat": 43.3751973, "lon": -8.4040266}, {"type": "node", "id": 6775537456, "lat": 43.3742771, "lon": -8.403908}, {"type": "node", "id": 6775537460, "lat": 43.3738851, "lon": -8.4040367}, {"type": "node", "id": 6775537461, "lat": 43.3734397, "lon": -8.4041762}, {"type": "node", "id": 6775537462, "lat": 43.3729972, "lon": -8.4043608}, {"type": "node", "id": 6775537463, "lat": 43.3726306, "lon": -8.4045544}, {"type": "node", "id": 6775537464, "lat": 43.3722556, "lon": -8.4048141}, {"type": "node", "id": 6775537465, "lat": 43.3718156, "lon": -8.4052183}, {"type": "node", "id": 6775537466, "lat": 43.3713443, "lon": -8.4056611}, {"type": "node", "id": 6775537467, "lat": 43.3709548, "lon": -8.4061034}, {"type": "node", "id": 6775537468, "lat": 43.3705216, "lon": -8.4066769}, {"type": "node", "id": 6775537469, "lat": 43.370132, "lon": -8.4072568}, {"type": "node", "id": 6775537470, "lat": 43.369859, "lon": -8.4077141}, {"type": "node", "id": 6775537471, "lat": 43.3697843, "lon": -8.4079127}, {"type": "node", "id": 6775537472, "lat": 43.3697599, "lon": -8.4080494}, {"type": "node", "id": 6775537473, "lat": 43.3697606, "lon": -8.4080775}, {"type": "node", "id": 6775537474, "lat": 43.3697693, "lon": -8.4081023}, {"type": "node", "id": 6775537476, "lat": 43.3697708, "lon": -8.4081285}, {"type": "node", "id": 6775537478, "lat": 43.3697796, "lon": -8.4081499}, {"type": "node", "id": 6775537480, "lat": 43.369784, "lon": -8.4081801}, {"type": "node", "id": 6775537482, "lat": 43.3696918, "lon": -8.4084202}, {"type": "node", "id": 6775537484, "lat": 43.3696309, "lon": -8.4085419}, {"type": "node", "id": 6775545385, "lat": 43.3695581, "lon": -8.4086714}, {"type": "node", "id": 6775545386, "lat": 43.3694876, "lon": -8.4088077}, {"type": "node", "id": 6775545387, "lat": 43.3694246, "lon": -8.4089526}, {"type": "node", "id": 6775545388, "lat": 43.3693726, "lon": -8.4090626}, {"type": "node", "id": 6775545389, "lat": 43.369337, "lon": -8.4091578}, {"type": "node", "id": 6775545390, "lat": 43.3693095, "lon": -8.409273}, {"type": "node", "id": 6775545391, "lat": 43.369253, "lon": -8.4095129}, {"type": "node", "id": 6775545392, "lat": 43.369219, "lon": -8.4097391}, {"type": "node", "id": 6775545393, "lat": 43.3691577, "lon": -8.4100614}, {"type": "node", "id": 6775545394, "lat": 43.3691355, "lon": -8.4102999}, {"type": "node", "id": 6775545395, "lat": 43.3690993, "lon": -8.4104721}, {"type": "node", "id": 6775545396, "lat": 43.3690582, "lon": -8.4106057}, {"type": "node", "id": 6775545397, "lat": 43.3690206, "lon": -8.4108006}, {"type": "node", "id": 6775545398, "lat": 43.3690257, "lon": -8.4109343}, {"type": "node", "id": 6775545399, "lat": 43.3690504, "lon": -8.4110862}, {"type": "node", "id": 6775545400, "lat": 43.3690532, "lon": -8.4112618}, {"type": "node", "id": 6775545401, "lat": 43.3690057, "lon": -8.4115121}, {"type": "node", "id": 6775545403, "lat": 43.368971, "lon": -8.411829}, {"type": "node", "id": 6775545404, "lat": 43.3689817, "lon": -8.4121707}, {"type": "node", "id": 6775545405, "lat": 43.3690107, "lon": -8.4123818}, {"type": "node", "id": 6775545406, "lat": 43.3690511, "lon": -8.4126274}, {"type": "node", "id": 6775545407, "lat": 43.3690978, "lon": -8.4128185}, {"type": "node", "id": 6775545408, "lat": 43.3691531, "lon": -8.4129442}, {"type": "node", "id": 6775545409, "lat": 43.3692162, "lon": -8.41299}, {"type": "node", "id": 6775545410, "lat": 43.3692956, "lon": -8.4130056}, {"type": "node", "id": 6775545412, "lat": 43.369316, "lon": -8.4131549}, {"type": "node", "id": 6775545413, "lat": 43.3693845, "lon": -8.4134805}, {"type": "node", "id": 6775545414, "lat": 43.369467, "lon": -8.413727}, {"type": "node", "id": 6775545415, "lat": 43.3697854, "lon": -8.4142139}, {"type": "node", "id": 6775545417, "lat": 43.369782, "lon": -8.4142046}, {"type": "node", "id": 6775545419, "lat": 43.3697795, "lon": -8.4141725}, {"type": "node", "id": 6775545421, "lat": 43.3697721, "lon": -8.4141447}, {"type": "node", "id": 6775545423, "lat": 43.3697604, "lon": -8.4141364}, {"type": "node", "id": 6775545425, "lat": 43.3697349, "lon": -8.4141501}, {"type": "node", "id": 6775545427, "lat": 43.3697225, "lon": -8.4141372}, {"type": "node", "id": 6775545429, "lat": 43.3698827, "lon": -8.4142734}, {"type": "node", "id": 6775545430, "lat": 43.3698529, "lon": -8.4142612}, {"type": "node", "id": 6775545431, "lat": 43.3698224, "lon": -8.4142397}, {"type": "node", "id": 6775545432, "lat": 43.3696329, "lon": -8.4140116}, {"type": "node", "id": 6775545433, "lat": 43.3695328, "lon": -8.4138646}, {"type": "node", "id": 7866607606, "lat": 43.382115, "lon": -8.3962348}, {"type": "node", "id": 7866607607, "lat": 43.3820972, "lon": -8.3962104}, {"type": "way", "id": 39472001, "nodes": [1695373562, 6775537456, 6775537460, 6775537461, 6775537462, 6775537463, 6775537464, 6775537465, 6775537466, 6775537467, 6775537468, 6775537469, 6775537470, 6775537471, 6775537472, 5406109822, 5406109823, 6773051669, 6773051672, 6773051673, 6773051675, 6773051677, 5406109826, 5406109828, 6314600545, 472690415, 5406109831, 472690416, 6314600547, 5667468551, 5667468555, 5667492631, 5667492621, 5667492630, 5670446567, 4884182014, 5670446566, 5670446564, 4884182015, 5670446565, 472690417, 5667492628, 472690418, 472690419, 5670446573, 5406109834, 5670446572, 5406109833, 5406109835, 5670446571, 472690420, 5667503727, 472690421, 5670446581, 5667503737, 5670446579, 5670446580, 5670446584, 5670446576, 5406109838, 5670446577, 5667501620, 5667503730, 5667503724, 472690423, 5667503722, 5667503725, 472690424, 5667523644, 5667523640, 472690425, 5667523649, 5667523645, 5406111541, 5667523651, 472690426, 5667523650, 5667523647, 5036761566, 6772428685, 5406117848, 5406117849, 1695373562], "tags": {"access": "yes", "name": "Praia do Orz\u00e1n", "name:en": "Orzan Beach", "name:es": "Playa del Orz\u00e1n", "name:gl": "Praia do Orz\u00e1n", "name:pt": "Praia do Or\u00e7\u00e3o", "natural": "beach", "surface": "sand", "wikipedia": "gl:Praia do Orz\u00e1n"}}, {"type": "way", "id": 39472002, "nodes": [6775537450, 6775537451, 1695373571, 5036761604, 5866419369, 5866419368, 5866419367, 6772395983, 5866440960, 5406111548, 5866440956, 6096930442, 472690429, 472690430, 3306648933, 472690431, 5866420851, 3306648907, 472690432, 5866420693, 5866420694, 5866420696, 5036761344, 6775537447, 6775537449, 6775537450], "tags": {"access": "yes", "name": "Praia do Matadoiro", "name:es": "Playa del Matadero", "name:gl": "Praia do Matadoiro", "natural": "beach", "surface": "sand", "wikidata": "Q18576276", "wikipedia": "gl:Praia do Matadoiro"}}, {"type": "way", "id": 40012885, "nodes": [31606807, 6772415744, 6772415743, 480939708, 480939714, 480939718, 480939723, 6486398137, 480939734, 6486398130, 6486398131, 480939740, 6486398139, 480939745, 480939754, 6486398143, 6486398146, 7866607606, 7866607607, 6486398136, 31627679, 5499790390, 6772415741, 6772415742, 31618756, 5499790391, 31606807], "tags": {"name": "Praia de Santo Amaro", "name:es": "Playa de San Amaro", "name:gl": "Praia de Santo Amaro", "natural": "beach", "surface": "sand", "wikidata": "Q20546375", "wikipedia": "gl:Praia de Santo Amaro"}}, {"type": "way", "id": 70771720, "nodes": [31635031, 843945429, 843945427, 844086949, 844086950, 844086952, 844086953, 844086954, 31635031], "tags": {"name": "Praia do Co\u00eddo", "natural": "beach", "short_name": "O Co\u00eddo", "source": "PNOA;Mural \"A ruta do sabio percebeiro Milucho Mari\u00f1as\" no Club de Mar de Santo Amaro", "surface": "pebblestone"}}, {"type": "way", "id": 70771729, "nodes": [843945226, 843945224, 844086958, 844086959, 844086960, 844086961, 844086962, 844086963, 844086964, 844086967, 843945226], "tags": {"alt_name": "Praia da Cuncha", "name": "Praia de Durmideiras", "name:es": "Playa de Adormideras", "name:gl": "Praia de Durmideiras", "natural": "beach", "surface": "sand", "wikidata": "Q18576054", "wikipedia": "gl:Praia de Durmideiras"}}, {"type": "way", "id": 70771737, "nodes": [843945206, 843945209, 844086971, 844086973, 844086975, 844086976, 844086978, 843945206], "tags": {"alt_name": "Area da Cuncha", "name": "Praia do Mouro", "natural": "beach", "surface": "sand"}}, {"type": "way", "id": 159191647, "nodes": [1712869471, 5884578513, 5884578514, 5884578515, 5884578516, 5884578517, 480761387, 5884578512, 5884578511, 480761388, 5884563413, 5884563414, 5884563415, 5884563416, 5884563417, 5884563418, 5884563419, 1712869477, 1712869480, 5884563420, 5884563421, 1712869483, 5884563423, 1712869489, 5884563424, 5884563425, 5884998005, 5884578601, 5884578602, 5884563427, 5884996913, 5884563428, 5885001881, 5884563429, 5884563430, 1712869471], "tags": {"access": "yes", "name": "Praia de San Roque-Cetaria", "name:es": "Playa de San Roque-Cet\u00e1rea", "name:gl": "Praia de San Roque-Cetaria", "natural": "beach", "surface": "sand"}}, {"type": "way", "id": 204396547, "nodes": [2144030343, 5673396215, 5673396214, 5673396213, 2144030421, 5673396209, 5673396211, 5673396210, 2144030355, 5884547519, 5884547520, 5884547521, 2144030349, 5884547518, 5884547517, 1695373526, 5884547516, 5884547515, 1695373524, 5884547514, 1695373525, 5884547513, 5884547512, 1695373528, 5884547511, 5884547510, 2420103239, 5884547522, 5884563396, 2144030343], "tags": {"access": "yes", "name": "Praia de San Roque", "name:es": "Playa de San Roque", "natural": "beach", "surface": "rock", "wikidata": "Q12398092"}}, {"type": "way", "id": 204396555, "nodes": [2144030402, 5884547309, 2420101291, 5884546681, 5673397035, 5673397034, 5673397053, 2144030351, 5673397025, 2144030372, 5884547379, 5884547380, 5884547381, 5884547382, 5884547383, 5884547384, 5884547385, 5884547386, 2144030365, 5884547387, 5884547388, 5884547389, 5884547390, 5884547391, 5884547392, 1695373549, 5884547378, 5884547377, 5884547376, 1695373546, 5884547375, 1695373548, 5884547374, 1695373550, 5884547373, 1695373551, 5884547368, 5884547367, 5884547366, 5884547365, 5884547364, 5884547363, 2144030381, 5884547362, 5884547361, 5884547360, 5884547359, 5884547358, 5884547357, 2144030402], "tags": {"access": "yes", "name": "Praia de San Roque-Lino", "natural": "beach", "surface": "sand"}}, {"type": "way", "id": 235028338, "nodes": [472690434, 5667219027, 5667204497, 5667219025, 472690435, 5670442788, 5670442789, 5667219028, 5670442790, 472690436, 5667248867, 5670446530, 5667274023, 5670446529, 5667248841, 5667274026, 5670446528, 5670446539, 5667248880, 5670446540, 472690437, 5667267319, 5670446538, 5667267633, 5670446537, 5670446535, 5667267629, 5670446536, 5667248887, 5667248869, 472690438, 5670446544, 5667267311, 5670446545, 5667267313, 5670446548, 5670446550, 5670446551, 5670446552, 5670446549, 5667267314, 472690439, 5667281034, 5667281044, 5667281036, 472690440, 5667285730, 5667285726, 5670446557, 5670446555, 5667285722, 5670446556, 5667285724, 472690441, 5667313602, 4884196710, 5670446560, 5670446558, 4884196711, 5670446559, 472690442, 5667438975, 5667468561, 472690443, 472690444, 5036761596, 5406109821, 5667468560, 5667468556, 5406109823, 5406109822, 6775537472, 6775537473, 6775537474, 6775537476, 6775537478, 6775537480, 6775537482, 6775537484, 6775545385, 6775545386, 6775545387, 6775545388, 6775545389, 6775545390, 6775545391, 6775545392, 6775545393, 6775545394, 6775545395, 6775545396, 6775545397, 6775545398, 6775545399, 6775545400, 6775545401, 6775545403, 6775545404, 6775545405, 6775545406, 6775545407, 6775545408, 6775545409, 6775545410, 6775545412, 6775545413, 6775545414, 6775545433, 6775545432, 6775545427, 6775545425, 6775545423, 6775545421, 6775545419, 6775545417, 6775545415, 5884526789, 6775545431, 6775545430, 6775545429, 5884526877, 5884526876, 5884526875, 1695373521, 5884526874, 5884526873, 5884526872, 5884526871, 5884526870, 5884526869, 5884526868, 5884526861, 5884526860, 5884526859, 5884526858, 5884526857, 5884526867, 5884526856, 5884526855, 5884526862, 5884526854, 5884526853, 5884526852, 5884526851, 5884526850, 5884526849, 5884526848, 5884526847, 5884526846, 5884526845, 5884526844, 5884526843, 5884526842, 5884526841, 5884526840, 5884526839, 5884526838, 5884526837, 5884526836, 5884526835, 5884526834, 5884526833, 5884526832, 5884526831, 5884526830, 5884526829, 5884526828, 5884526827, 5884526826, 5884526825, 5884526824, 5884526823, 6399259994, 6399259995, 5884526864, 5667204482, 5885266205, 5667204476, 5667204500, 5670442791, 472690434], "tags": {"access": "yes", "name": "Praia de Riazor", "name:en": "Riazor Beach", "name:es": "Playa de Riazor", "name:gl": "Praia de Riazor", "name:pt": "Praia de Ria\u00e7or", "natural": "beach", "surface": "sand", "wikipedia": "gl:Praia de Riazor"}}, {"type": "way", "id": 297923884, "nodes": [3018266453, 5871751290, 3018266454, 5871751291, 5871751292, 5871751293, 5871751294, 5871751296, 5871751295, 5871751289, 5871751288, 5871751287, 5871751286, 5871750361, 5871751285, 3018266456, 5871750384, 5871750383, 31618230, 1695373581, 5869331542, 5869331543, 3018266453], "tags": {"alt_name": "Praia das Amorosas", "loc_name": "Praia de Sislar", "name": "Praia das Morosas", "natural": "beach", "short_name": "Praia As Morosas", "surface": "pebblestone"}}, {"type": "way", "id": 515838973, "nodes": [5872134802, 844087005, 844087008, 844087011, 6772415756, 6772415755, 6772415754, 6772415753, 5872150594, 5036761610, 6773275378, 6773275379, 5872149709, 6773275380, 6773275381, 6773275382, 5036761612, 31626707, 1870878283, 1870878281, 844086989, 1870878280, 1870878279, 1870878278, 844086991, 1870878275, 1870878274, 1870878273, 1870878271, 844086997, 844086998, 1870878266, 1870878267, 844087000, 844087004, 5872134802], "tags": {"alt_name": "Praia do Areal", "name": "Praia das Lapas", "natural": "beach", "surface": "sand", "wikidata": "Q18576114", "wikipedia": "gl:Praia das Lapas"}}, {"type": "way", "id": 515838982, "nodes": [5036761555, 5885137903, 5885137902, 5885137901, 5885137900, 5885137904, 5885137899, 5885137898, 5885137897, 480761428, 5885137906, 5885137907, 5885137908, 5885137909, 5885137910, 5885137911, 5885137912, 5885137905, 31622371, 5885139212, 5036761585, 5885139213, 5885139214, 5885139215, 5885139216, 5885139217, 5885139218, 5885139219, 5036761405, 5036761555], "tags": {"natural": "beach", "surface": "pebblestone"}}, {"type": "way", "id": 572468559, "nodes": [1695377134, 4582881807, 4582881723, 4582881818, 2617061864, 2617061862, 2617061859, 2617061861, 2617061858, 2617061860, 2617061857, 31610575, 1695377134], "tags": {"natural": "beach"}}, {"type": "way", "id": 572468561, "nodes": [5499790213, 31620591, 5499790214, 4582881800, 4582881799, 4582881691, 4582881736, 4582881750, 5499790213], "tags": {"natural": "beach"}}]}