[{"place_id": 308376818, "licence": "Data \u00a9 OpenStreetMap contributors, ODbL 1.0. https://osm.org/copyright", "osm_type": "relation", "osm_id": 5320138, "boundingbox": ["-30.036972", "-30.03023", "-51.2206676", "-51.2082652"], "lat": "-30.0333968", "lon": "-51.2117199", "display_name": "Bom Fim, Porto Alegre, Regi\u00e3o Geogr\u00e1fica Imediata de Porto Alegre, Metropolitan Region of Porto Alegre, Regi\u00e3o Geogr\u00e1fica Intermedi\u00e1ria de Porto Alegre, Rio Grande do Sul, South Region, Brazil", "class": "boundary", "type": "administrative", "importance": 0.7434252226761786, "icon": "https://nominatim.openstreetmap.org/ui/mapicons/poi_boundary_administrative.p.20.png"}]